walt/__init__.py
walt/client/__init__.py
walt/client/advanced.py
walt/client/apitools.py
walt/client/application.py
walt/client/auth.py
walt/client/client.py
walt/client/config.py
walt/client/console.py
walt/client/device.py
walt/client/exceptions.py
walt/client/expose.py
walt/client/filesystem.py
walt/client/image.py
walt/client/interactive.py
walt/client/link.py
walt/client/log.py
walt/client/logo.py
walt/client/myhelp.py
walt/client/node.py
walt/client/plugins.py
walt/client/progress.py
walt/client/speedup.py
walt/client/startup.py
walt/client/timeout.py
walt/client/tools.py
walt/client/transfer.py
walt/client/types.py
walt/client/update.py
walt/client/wrap.py
walt/client/apiobject/__init__.py
walt/client/apiobject/base.py
walt/client/apiobject/config.py
walt/client/apiobject/images.py
walt/client/apiobject/logs.py
walt/client/apiobject/nodes.py
walt/client/apiobject/root.py
walt/client/apiobject/server.py
walt/client/apiobject/tools.py
walt/client/autocomplete/__init__.py
walt/client/autocomplete/dump.py
walt/client/autocomplete/helper.py
walt/client/metadata/__init__.py
walt/client/metadata/core.py
walt_client-10.0.dist-info/METADATA
walt_client-10.0.dist-info/WHEEL
walt_client-10.0.dist-info/entry_points.txt
walt_client-10.0.dist-info/top_level.txt
walt_client-10.0.dist-info/RECORD
